{
  "@timestamp": "2026-04-07T12:00:00.000Z",
  "ecs": { "version": "8.11.0" },
  "cloud": {
    "provider": "azure",
    "region": "swedencentral",
    "account": { "id": "c4a2d8f6-3b91-4e7c-a5d2-9e1f0c8b7a6d", "name": "Northpeak-Dev" },
    "service": { "name": "azure.api_management_metrics" }
  },
  "agent": {
    "type": "metricbeat",
    "version": "8.18.0",
    "name": "metricbeat-azure-swedencentral",
    "ephemeral_id": "t9mf3u8m0zabkxu7huisd837946d9znnw5xq"
  },
  "azure": {
    "api_management": {
      "metrics": {
        "Requests": {
          "avg": 211216,
          "min": 185870.08,
          "max": 236561.92,
          "sum": 211216,
          "count": 1
        },
        "Duration": { "avg": 167.29, "min": 147.22, "max": 187.36, "sum": 167.29, "count": 1 },
        "Bandwidth": {
          "avg": 8389752439,
          "min": 7382982146.32,
          "max": 9396522731.68,
          "sum": 8389752439,
          "count": 1
        },
        "FailedRequests": { "avg": 1403, "min": 1234.64, "max": 1571.36, "sum": 1403, "count": 1 },
        "SuccessfulRequests": {
          "avg": 660720,
          "min": 581433.6,
          "max": 740006.4,
          "sum": 660720,
          "count": 1
        },
        "UnauthorizedRequests": { "avg": 59, "min": 51.92, "max": 66.08, "sum": 59, "count": 1 }
      }
    },
    "dimensions": {
      "Gateway": "apim-iqoav",
      "ApiId": "orders-api",
      "ResourceGroup": "rg-data-p36us"
    },
    "resource": {
      "id": "/subscriptions/c4a2d8f6-3b91-4e7c-a5d2-9e1f0c8b7a6d/resourceGroups/rg-data-p36us/providers/Microsoft.ApiManagement/service/apim-iqoav",
      "group": "rg-data-p36us",
      "name": "apim-iqoav"
    },
    "namespace": "Microsoft.ApiManagement/service"
  },
  "metricset": { "name": "monitor", "period": 60000 },
  "data_stream": {
    "type": "metrics",
    "dataset": "azure.api_management_metrics",
    "namespace": "default"
  },
  "input": { "type": "azure-monitor" },
  "event": { "kind": "metric", "dataset": "azure.api_management_metrics", "module": "azure" },
  "azureMonitorMetric": {
    "time": "2026-04-07T12:00:00.000Z",
    "metricName": "Requests",
    "resourceGroup": "rg-api-management",
    "subscriptionId": "c4a2d8f6-3b91-4e7c-a5d2-9e1f0c8b7a6d",
    "timeseries": [{ "data": [{ "average": 211216, "count": 1 }] }]
  }
}
