{
  "@timestamp": "2026-04-07T12:00:00.000Z",
  "ecs": { "version": "8.11.0" },
  "cloud": {
    "provider": "azure",
    "region": "germanywestcentral",
    "account": { "id": "a3f8c2e1-7b4d-4f9a-8e2c-1d5f6a7b8c9d", "name": "Meridian-Platform" },
    "service": { "name": "azure.api_management_metrics" }
  },
  "agent": {
    "type": "metricbeat",
    "version": "8.18.0",
    "name": "metricbeat-azure-germanywestcentral",
    "ephemeral_id": "rfshsdhpdk8aaemwvqr01mkkmsirz3qv9cie"
  },
  "azure": {
    "api_management": {
      "metrics": {
        "Requests": {
          "avg": 1221367,
          "min": 1074802.96,
          "max": 1367931.04,
          "sum": 1221367,
          "count": 1
        },
        "Duration": { "avg": 88.37, "min": 77.77, "max": 98.97, "sum": 88.37, "count": 1 },
        "Bandwidth": {
          "avg": 8087987923,
          "min": 7117429372.24,
          "max": 9058546473.76,
          "sum": 8087987923,
          "count": 1
        },
        "FailedRequests": { "avg": 1224, "min": 1077.12, "max": 1370.88, "sum": 1224, "count": 1 },
        "SuccessfulRequests": {
          "avg": 1473688,
          "min": 1296845.44,
          "max": 1650530.56,
          "sum": 1473688,
          "count": 1
        },
        "UnauthorizedRequests": { "avg": 167, "min": 146.96, "max": 187.04, "sum": 167, "count": 1 }
      }
    },
    "dimensions": {
      "Gateway": "apim-opty3",
      "ApiId": "orders-api",
      "ResourceGroup": "rg-shared-bc45j"
    },
    "resource": {
      "id": "/subscriptions/a3f8c2e1-7b4d-4f9a-8e2c-1d5f6a7b8c9d/resourceGroups/rg-shared-bc45j/providers/Microsoft.ApiManagement/service/apim-opty3",
      "group": "rg-shared-bc45j",
      "name": "apim-opty3"
    },
    "namespace": "Microsoft.ApiManagement/service"
  },
  "metricset": { "name": "monitor", "period": 60000 },
  "data_stream": {
    "type": "metrics",
    "dataset": "azure.api_management_metrics",
    "namespace": "default"
  },
  "input": { "type": "azure-monitor" },
  "event": { "kind": "metric", "dataset": "azure.api_management_metrics", "module": "azure" },
  "azureMonitorMetric": {
    "time": "2026-04-07T12:00:00.000Z",
    "metricName": "Requests",
    "resourceGroup": "rg-api-management",
    "subscriptionId": "a3f8c2e1-7b4d-4f9a-8e2c-1d5f6a7b8c9d",
    "timeseries": [{ "data": [{ "average": 1221367, "count": 1 }] }]
  }
}
