{
  "@timestamp": "2026-04-04T12:00:00.000Z",
  "cloud": {
    "provider": "gcp",
    "region": "northamerica-northeast1",
    "project": { "id": "globex-shared-m3n4o5", "name": "Globex Shared Services" },
    "account": { "id": "173205080756", "name": "Globex Shared Services" },
    "service": { "name": "anthos-service-mesh" }
  },
  "gcp": {
    "anthos_service_mesh": {
      "mesh_name": "mesh-wf8d0",
      "service": "catalog.items",
      "source_workload": "default/collector-m38oi-a19ob",
      "dest_workload": "kube-system/collector-c1917-j97qq",
      "request_count": 326115,
      "latency_p99_ms": 316,
      "error_rate": 0.018,
      "protocol": "HTTP"
    }
  },
  "event": {
    "outcome": "success",
    "duration": 28451,
    "module": "gcp",
    "dataset": "gcp.anthos_mesh"
  },
  "message": "Anthos Service Mesh mesh-wf8d0 default/collector-m38oi-a19ob -> kube-system/collector-c1917-j97qq rq=326115 p99=316ms",
  "service": { "name": "anthos-service-mesh", "type": "gcp" },
  "log": { "level": "info" },
  "ecs": { "version": "8.11.0" },
  "data_stream": { "type": "logs", "dataset": "gcp.anthos_mesh", "namespace": "default" },
  "agent": {
    "type": "elastic-agent",
    "version": "8.18.0",
    "name": "elastic-agent-gcp-northamerica-northeast1",
    "id": "y7d2d3hozao"
  },
  "input": { "type": "gcp-pubsub" },
  "logName": "projects/globex-shared-m3n4o5/logs/anthos-service-mesh",
  "resource": {
    "type": "global",
    "labels": { "project_id": "globex-shared-m3n4o5", "region": "northamerica-northeast1" }
  },
  "severity": "INFO",
  "insertId": "PEVONC9K8Z",
  "jsonPayload": {
    "anthos_service_mesh": {
      "mesh_name": "mesh-wf8d0",
      "service": "catalog.items",
      "source_workload": "default/collector-m38oi-a19ob",
      "dest_workload": "kube-system/collector-c1917-j97qq",
      "request_count": 326115,
      "latency_p99_ms": 316,
      "error_rate": 0.018,
      "protocol": "HTTP"
    },
    "message": "Anthos Service Mesh mesh-wf8d0 default/collector-m38oi-a19ob -> kube-system/collector-c1917-j97qq rq=326115 p99=316ms"
  }
}
