{
  "@timestamp": "2026-04-04T12:00:00.000Z",
  "cloud": {
    "provider": "gcp",
    "region": "asia-south2",
    "project": { "id": "globex-security-j0k1l2", "name": "Globex Security" },
    "account": { "id": "141421356237", "name": "Globex Security" },
    "service": { "name": "cloud-shell" }
  },
  "gcp": {
    "cloud_shell": {
      "session_id": "cloudshell-vx2hk24j5nn",
      "machine_type": "e2-medium",
      "event_type": "FILE_UPLOAD",
      "shell_type": "zsh",
      "storage_used_mb": 3188
    }
  },
  "event": { "outcome": "success", "duration": 9086, "module": "gcp", "dataset": "gcp.cloudshell" },
  "message": "Cloud Shell cloudshell-vx2hk24j5nn FILE_UPLOAD on e2-medium (zsh, 3188MB used)",
  "service": { "name": "cloud-shell", "type": "gcp" },
  "log": { "level": "info" },
  "ecs": { "version": "8.11.0" },
  "data_stream": { "type": "logs", "dataset": "gcp.cloudshell", "namespace": "default" },
  "agent": {
    "type": "elastic-agent",
    "version": "8.18.0",
    "name": "elastic-agent-gcp-asia-south2",
    "id": "kd6agy6bps8"
  },
  "input": { "type": "gcp-pubsub" },
  "logName": "projects/globex-security-j0k1l2/logs/cloud-shell",
  "resource": {
    "type": "global",
    "labels": { "project_id": "globex-security-j0k1l2", "region": "asia-south2" }
  },
  "severity": "INFO",
  "insertId": "TNDSHVZ36OE",
  "jsonPayload": {
    "cloud_shell": {
      "session_id": "cloudshell-vx2hk24j5nn",
      "machine_type": "e2-medium",
      "event_type": "FILE_UPLOAD",
      "shell_type": "zsh",
      "storage_used_mb": 3188
    },
    "message": "Cloud Shell cloudshell-vx2hk24j5nn FILE_UPLOAD on e2-medium (zsh, 3188MB used)"
  }
}
