{
  "@timestamp": "2026-04-04T12:00:00.000Z",
  "processor": { "name": "transaction", "event": "transaction" },
  "trace": { "id": "95cd6f0af64908f534356fda4e32494e" },
  "transaction": {
    "id": "fba4fbdc84480252",
    "name": "transaction",
    "type": "request",
    "duration": { "us": 2587260 },
    "result": "success",
    "sampled": true,
    "span_count": { "started": 7, "dropped": 0 }
  },
  "service": {
    "name": "inventory-service",
    "environment": "staging",
    "language": { "name": "python" },
    "runtime": { "name": "python", "version": "3.12" }
  },
  "cloud": {
    "provider": "gcp",
    "region": "us-west2",
    "project": { "id": "globex-shared-m3n4o5", "name": "Globex Shared Services" },
    "account": { "id": "173205080756", "name": "Globex Shared Services" },
    "service": { "name": "firestore.googleapis.com" }
  },
  "agent": { "name": "opentelemetry/nodejs", "version": "1.x" },
  "data_stream": { "type": "traces", "dataset": "apm", "namespace": "default" },
  "event": { "outcome": "success", "module": "gcp", "dataset": "gcp.firestore" },
  "ecs": { "version": "8.11.0" },
  "input": { "type": "opentelemetry" },
  "gcpCloudTrace": {
    "trace": "projects/globex-shared-m3n4o5/traces/95cd6f0af64908f534356fda4e32494e",
    "spanId": "fba4fbdc84480252"
  },
  "telemetry": {
    "sdk": { "name": "opentelemetry", "language": "python", "version": "1.29.0" },
    "distro": { "name": "elastic", "version": "8.18.0" },
    "otel_pipeline": {
      "hop": "otel_collector",
      "export_protocol": "otlp",
      "destination": "elastic_managed"
    }
  }
}
