{
  "@timestamp": "2026-04-10T08:43:15.441Z",
  "processor": { "name": "transaction", "event": "transaction" },
  "trace": { "id": "954a1e40d14608c5a13d25881f08968c" },
  "transaction": {
    "id": "add23d3046ee6e0b",
    "name": "structured-logs-stream process",
    "type": "messaging",
    "duration": { "us": 1551000 },
    "result": "success",
    "sampled": true,
    "span_count": { "started": 2, "dropped": 0 }
  },
  "labels": {
    "stream_name": "structured-logs-stream",
    "stream_arn": "arn:aws:kinesis:ap-southeast-1:234567890123:stream/structured-logs-stream",
    "shard_id": "shardId-000000000005",
    "sequence_number_range": "49237...49134",
    "record_count": "269",
    "iterator_age_ms": "15577"
  },
  "service": {
    "name": "log-aggregator",
    "environment": "staging",
    "version": "1.0.0",
    "language": { "name": "java" },
    "runtime": { "name": "java21", "version": "21.0.3" },
    "framework": { "name": "AWS Kinesis" }
  },
  "agent": { "name": "otlp", "version": "1.6.0" },
  "telemetry": {
    "sdk": { "name": "opentelemetry", "language": "java", "version": "2.12.0" },
    "distro": { "name": "elastic", "version": "1.6.0" },
    "otel_pipeline": {
      "hop": "otel_collector",
      "export_protocol": "otlp",
      "destination": "elastic_managed"
    }
  },
  "cloud": {
    "provider": "aws",
    "region": "ap-southeast-1",
    "account": { "id": "234567890123", "name": "staging-aws" },
    "service": { "name": "kinesis" }
  },
  "event": { "outcome": "success", "module": "aws", "dataset": "aws.kinesis" },
  "data_stream": { "type": "traces", "dataset": "apm", "namespace": "default" },
  "ecs": { "version": "8.11.0" },
  "input": { "type": "opentelemetry" }
}
