{
  "@timestamp": "2026-06-01T18:11:59.613Z",
  "ecs": { "version": "8.11.0" },
  "cloud": {
    "provider": "aws",
    "region": "sa-east-1",
    "account": { "id": "164820739518", "name": "globex-shared-services" },
    "service": { "name": "apprunner" }
  },
  "agent": {
    "type": "metricbeat",
    "version": "8.18.0",
    "name": "metricbeat-aws-sa-east-1",
    "ephemeral_id": "yik7tvu81wiybw1l3kbp0ex7c0xolykzrjq2"
  },
  "aws": {
    "apprunner": {
      "metrics": {
        "Requests": { "avg": 34764, "sum": 34764, "count": 1 },
        "Http2xxRequests": { "avg": 34236, "sum": 34236, "count": 1 },
        "Http4xxRequests": { "avg": 480, "sum": 480, "count": 1 },
        "Http5xxRequests": { "avg": 48, "sum": 48, "count": 1 },
        "RequestLatency": { "avg": 33.51, "sum": 33.51, "count": 1, "max": 651.67, "min": 5.27 },
        "RequestLatencyP50": { "avg": 41.98, "sum": 41.98, "count": 1, "max": 239.57, "min": 3.58 },
        "RequestLatencyP95": {
          "avg": 209.03,
          "sum": 209.03,
          "count": 1,
          "max": 677.94,
          "min": 43.36
        },
        "RequestLatencyP99": {
          "avg": 573.38,
          "sum": 573.38,
          "count": 1,
          "max": 1868.99,
          "min": 203.56
        },
        "ActiveInstances": { "avg": 7, "sum": 7, "count": 1 },
        "ConcurrentConnections": { "avg": 579.47, "sum": 579.47, "count": 1 },
        "MaxConcurrentConnections": { "avg": 693.15, "sum": 693.15, "count": 1 },
        "CPUUtilization": { "avg": 72.39, "sum": 72.39, "count": 1 },
        "MemoryUtilization": { "avg": 40.33, "sum": 40.33, "count": 1 }
      },
      "dimensions": { "ServiceName": "frontend" }
    }
  },
  "metricset": { "name": "apprunner", "period": 60000 },
  "data_stream": { "type": "metrics", "dataset": "aws.apprunner", "namespace": "default" },
  "input": { "type": "aws-cloudwatch" },
  "event": { "kind": "metric", "dataset": "aws.apprunner", "module": "aws" }
}
