{
  "@timestamp": "2026-04-13T15:46:43.100Z",
  "ecs": { "version": "8.11.0" },
  "cloud": {
    "provider": "aws",
    "region": "eu-north-1",
    "account": { "id": "501938274650", "name": "globex-security-tooling" }
  },
  "agent": {
    "type": "metricbeat",
    "version": "8.18.0",
    "name": "metricbeat-aws-eu-north-1",
    "ephemeral_id": "70lufw2idkm"
  },
  "aws": {
    "budgets": {
      "metrics": {
        "RequestCount": { "avg": 241693, "sum": 241693, "count": 1 },
        "ErrorCount": { "avg": 0, "sum": 0, "count": 1 },
        "SuccessCount": { "avg": 714349, "sum": 714349, "count": 1 }
      },
      "dimensions": { "Region": "us-east-1" }
    }
  },
  "metricset": { "name": "budgets", "period": 60000 },
  "data_stream": { "type": "metrics", "dataset": "aws.budgets", "namespace": "default" },
  "input": { "type": "aws-cloudwatch" },
  "event": { "dataset": "aws.budgets", "module": "aws" }
}
