{
  "@timestamp": "2026-04-09T10:32:55.502Z",
  "ecs": { "version": "8.11.0" },
  "cloud": {
    "provider": "aws",
    "region": "ap-northeast-1",
    "account": { "id": "738291046572", "name": "globex-development" }
  },
  "agent": {
    "type": "metricbeat",
    "version": "8.18.0",
    "name": "metricbeat-aws-ap-northeast-1",
    "ephemeral_id": "kkl26kc8o3l"
  },
  "aws": {
    "glue": {
      "metrics": {
        "glue_ALL_executors": { "avg": 17, "sum": 17, "count": 1 },
        "glue_FAILED_executors": { "avg": 0, "sum": 0, "count": 1 },
        "glue_WAITING_executors": { "avg": 1, "sum": 1, "count": 1 },
        "glue_driver_jvm_heap_usage": { "avg": 56.22, "sum": 56.22, "count": 1 },
        "glue_driver_aggregate_bytesRead": { "avg": 79942802908, "sum": 79942802908, "count": 1 },
        "glue_driver_aggregate_bytesWritten": { "avg": 3843704125, "sum": 3843704125, "count": 1 },
        "glue_driver_aggregate_recordsRead": { "avg": 153604275, "sum": 153604275, "count": 1 },
        "glue_driver_aggregate_numFiles": { "avg": 7309, "sum": 7309, "count": 1 },
        "glue_driver_aggregate_elapsedTime": { "avg": 90821.52, "sum": 90821.52, "count": 1 }
      },
      "dimensions": { "JobName": "parquet-converter", "JobRunId": "jr_l6ucht0icfc", "Type": "ETL" }
    }
  },
  "metricset": { "name": "glue", "period": 60000 },
  "data_stream": { "type": "metrics", "dataset": "aws.glue", "namespace": "default" },
  "input": { "type": "aws-cloudwatch" },
  "event": { "dataset": "aws.glue", "module": "aws" }
}
