{
  "@timestamp": "2026-05-19T12:26:13.277Z",
  "ecs": { "version": "8.11.0" },
  "cloud": {
    "provider": "aws",
    "region": "ap-northeast-1",
    "account": { "id": "293847561023", "name": "globex-staging" }
  },
  "agent": {
    "type": "metricbeat",
    "version": "8.18.0",
    "name": "metricbeat-aws-ap-northeast-1",
    "ephemeral_id": "wawffn34s3clliub0vdpzf7mualsvrab7t2b"
  },
  "aws": {
    "redshift": {
      "metrics": {
        "CPUUtilization": { "avg": 18.41, "sum": 18.41, "count": 1 },
        "PercentageDiskSpaceUsed": { "avg": 20.57, "sum": 20.57, "count": 1 },
        "DatabaseConnections": { "avg": 385, "sum": 385, "count": 1 },
        "HealthStatus": { "avg": 1, "sum": 1, "count": 1 },
        "MaintenanceMode": { "avg": 0, "sum": 0, "count": 1 },
        "QueryDuration": { "avg": 101.52, "sum": 101.52, "count": 1, "max": 42258.09 },
        "QueriesCompletedPerSecond": { "avg": 4.21, "sum": 4.21, "count": 1 },
        "NumExceededSchemaQuotas": { "avg": 0, "sum": 0, "count": 1 },
        "ReadLatency": { "avg": 0.02, "sum": 0.02, "count": 1 },
        "WriteLatency": { "avg": 0.02, "sum": 0.02, "count": 1 },
        "ReadIOPS": { "avg": 28079, "sum": 28079, "count": 1 },
        "WriteIOPS": { "avg": 4026, "sum": 4026, "count": 1 },
        "ReadThroughput": { "avg": 2257791866, "sum": 2257791866, "count": 1 },
        "WriteThroughput": { "avg": 1668672972, "sum": 1668672972, "count": 1 },
        "NetworkReceiveThroughput": { "avg": 8093563736, "sum": 8093563736, "count": 1 },
        "NetworkTransmitThroughput": { "avg": 9293212011, "sum": 9293212011, "count": 1 },
        "CommitQueueLength": { "avg": 0.39, "sum": 0.39, "count": 1 },
        "ConcurrencyScalingActiveClusters": { "avg": 0, "sum": 0, "count": 1 },
        "ConcurrencyScalingSeconds": { "avg": 0, "sum": 0, "count": 1 },
        "MaxConfiguredConcurrencyScalingClusters": { "avg": 5, "sum": 5, "count": 1 },
        "TotalTableCount": { "avg": 7665, "sum": 7665, "count": 1 }
      },
      "dimensions": { "ClusterIdentifier": "data-warehouse", "NodeID": "Leader" }
    }
  },
  "metricset": { "name": "redshift", "period": 60000 },
  "data_stream": { "type": "metrics", "dataset": "aws.redshift", "namespace": "default" },
  "input": { "type": "aws-cloudwatch" },
  "event": { "dataset": "aws.redshift", "module": "aws" }
}
