{
  "@timestamp": "2026-04-22T18:07:53.671Z",
  "ecs": { "version": "8.11.0" },
  "cloud": {
    "provider": "aws",
    "region": "us-west-2",
    "account": { "id": "501938274650", "name": "globex-security-tooling" }
  },
  "agent": {
    "type": "metricbeat",
    "version": "8.18.0",
    "name": "metricbeat-aws-us-west-2",
    "ephemeral_id": "k07o69yi328"
  },
  "aws": {
    "s3": {
      "metrics": {
        "BucketSizeBytes": { "avg": 480092518088704, "sum": 480092518088704, "count": 1 },
        "NumberOfObjects": { "avg": 488564088, "sum": 488564088, "count": 1 },
        "AllRequests": { "avg": 9583933, "sum": 9583933, "count": 1 },
        "GetRequests": { "avg": 244416, "sum": 244416, "count": 1 },
        "PutRequests": { "avg": 1564391, "sum": 1564391, "count": 1 },
        "DeleteRequests": { "avg": 299122, "sum": 299122, "count": 1 },
        "HeadRequests": { "avg": 797062, "sum": 797062, "count": 1 },
        "PostRequests": { "avg": 154658, "sum": 154658, "count": 1 },
        "SelectRequests": { "avg": 20293, "sum": 20293, "count": 1 },
        "ListRequests": { "avg": 352629, "sum": 352629, "count": 1 },
        "4xxErrors": { "avg": 1380, "sum": 1380, "count": 1 },
        "5xxErrors": { "avg": 428, "sum": 428, "count": 1 },
        "FirstByteLatency": { "avg": 785.82, "sum": 785.82, "count": 1, "max": 2442.91 },
        "TotalRequestLatency": { "avg": 151.04, "sum": 151.04, "count": 1, "max": 249.61 },
        "BytesDownloaded": { "avg": 192258821033, "sum": 192258821033, "count": 1 },
        "BytesUploaded": { "avg": 329882513116, "sum": 329882513116, "count": 1 },
        "SelectScannedBytes": { "avg": 43898113140, "sum": 43898113140, "count": 1 },
        "SelectReturnedBytes": { "avg": 801854045, "sum": 801854045, "count": 1 }
      },
      "dimensions": { "BucketName": "backups", "StorageType": "StandardIAStorage" }
    }
  },
  "metricset": { "name": "s3", "period": 60000 },
  "data_stream": { "type": "metrics", "dataset": "aws.s3_daily_storage", "namespace": "default" },
  "input": { "type": "aws-cloudwatch" },
  "event": { "dataset": "aws.s3_daily_storage", "module": "aws" }
}
