{
  "@timestamp": "2026-04-10T11:57:57.329Z",
  "cloud": {
    "provider": "aws",
    "region": "ap-east-1",
    "account": { "id": "814726593401", "name": "globex-production" },
    "service": { "name": "dsql" }
  },
  "aws": {
    "dimensions": { "ClusterId": "dsql-w0c3uk9mue", "RegionMode": "replica" },
    "auroradsql": {
      "cluster_id": "dsql-w0c3uk9mue",
      "linked_cluster_arns": ["arn:aws:dsql:us-east-1:814726593401:cluster/dsql-nl4uq3ku"],
      "transaction_id": "txn-7pzy16sni2a",
      "region_mode": "replica",
      "metrics": {
        "transactions_per_sec": 6701.48758965822,
        "storage_used_gb": 40.28485653554151,
        "replication_lag_ms": 73
      }
    },
    "s3": {
      "bucket": {
        "name": "aws-auroradsql-logs-814726593401",
        "arn": "arn:aws:s3:::aws-auroradsql-logs-814726593401"
      },
      "object": {
        "key": "AWSLogs/814726593401/auroradsql/ap-east-1/2026/04/10/auroradsql_78HWLZJPMNE.log.gz"
      }
    },
    "cloudwatch": {
      "log_group": "/aws/auroradsql/logs",
      "log_stream": "ap-east-1/kzfum7w7",
      "ingestion_time": "2026-04-10T11:57:57.791Z"
    }
  },
  "event": {
    "outcome": "success",
    "category": ["database"],
    "dataset": "aws.auroradsql",
    "provider": "dsql.amazonaws.com",
    "duration": 83000000,
    "module": "aws"
  },
  "data_stream": { "type": "logs", "dataset": "aws.auroradsql", "namespace": "default" },
  "message": "Aurora DSQL cluster dsql-w0c3uk9mue: 6701 TPS, storage=40.3GB, replication_lag=73ms",
  "log": { "level": "info" },
  "service": { "name": "auroradsql", "type": "aws" },
  "ecs": { "version": "8.11.0" },
  "agent": {
    "type": "filebeat",
    "version": "8.18.0",
    "name": "filebeat-aws-ap-east-1",
    "ephemeral_id": "fzbx3hhp47h"
  },
  "input": { "type": "aws-cloudwatch" }
}
