{
  "@timestamp": "2026-04-13T15:46:43.100Z",
  "cloud": {
    "provider": "aws",
    "region": "ap-southeast-2",
    "account": { "id": "738291046572", "name": "globex-development" },
    "service": { "name": "budgets" }
  },
  "aws": {
    "budgets": {
      "budget_name": "quarterly-compute",
      "budget_type": "RI_UTILIZATION",
      "time_period": "QUARTERLY",
      "currency": "USD",
      "budget_limit": 7942.24,
      "actual_spend": 4716.09,
      "forecasted_spend": 4449.09,
      "threshold_exceeded": false,
      "threshold_percentage": 60,
      "notification_type": "FORECASTED",
      "subscribers": "ops@company.com"
    },
    "s3": {
      "bucket": {
        "name": "aws-budgets-logs-738291046572",
        "arn": "arn:aws:s3:::aws-budgets-logs-738291046572"
      },
      "object": {
        "key": "AWSLogs/738291046572/budgets/ap-southeast-2/2026/04/13/budgets_IH51Y65RHWH.log.gz"
      }
    },
    "cloudwatch": {
      "log_group": "/aws/budgets/logs",
      "log_stream": "ap-southeast-2/9wonjqzm",
      "ingestion_time": "2026-04-13T15:46:43.627Z"
    }
  },
  "event": {
    "outcome": "success",
    "category": ["configuration", "process"],
    "dataset": "aws.budgets",
    "provider": "budgets.amazonaws.com",
    "duration": 27000000000,
    "module": "aws"
  },
  "message": "Budget OK: quarterly-compute at 4716/7942 (59%)",
  "log": { "level": "info" },
  "service": { "name": "budgets", "type": "aws" },
  "ecs": { "version": "8.11.0" },
  "data_stream": { "type": "logs", "dataset": "aws.budgets", "namespace": "default" },
  "agent": {
    "type": "filebeat",
    "version": "8.18.0",
    "name": "filebeat-aws-ap-southeast-2",
    "ephemeral_id": "3kp9gjkspha"
  },
  "input": { "type": "http_endpoint" }
}
