{
  "@timestamp": "2026-04-13T10:53:45.336Z",
  "cloud": {
    "provider": "aws",
    "region": "us-east-2",
    "account": { "id": "814726593401", "name": "globex-production" },
    "service": { "name": "codeartifact" }
  },
  "aws": {
    "codeartifact": {
      "domain_name": "platform",
      "repository_name": "nuget-store",
      "package_format": "maven",
      "package_name": "utils",
      "package_version": "2.11.4",
      "action": "DeletePackageVersions",
      "download_size_bytes": 28839163
    },
    "s3": {
      "bucket": {
        "name": "aws-codeartifact-logs-814726593401",
        "arn": "arn:aws:s3:::aws-codeartifact-logs-814726593401"
      },
      "object": {
        "key": "AWSLogs/814726593401/codeartifact/us-east-2/2026/04/13/codeartifact_ZQK3MY3AT8.log.gz"
      }
    },
    "cloudwatch": {
      "log_group": "/aws/codeartifact/logs",
      "log_stream": "us-east-2/i6dmgi7k",
      "ingestion_time": "2026-04-13T10:53:45.773Z"
    }
  },
  "event": {
    "action": "DeletePackageVersions",
    "outcome": "success",
    "category": ["package", "process"],
    "dataset": "aws.codeartifact",
    "provider": "codeartifact.amazonaws.com",
    "module": "aws"
  },
  "message": "CodeArtifact DeletePackageVersions: utils@2.11.4 [maven] in platform/nuget-store",
  "log": { "level": "info" },
  "service": { "name": "codeartifact", "type": "aws" },
  "ecs": { "version": "8.11.0" },
  "data_stream": { "type": "logs", "dataset": "aws.codeartifact", "namespace": "default" },
  "agent": {
    "type": "filebeat",
    "version": "8.18.0",
    "name": "filebeat-aws-us-east-2",
    "ephemeral_id": "tsjbmoe9sgh"
  },
  "input": { "type": "aws-cloudwatch" }
}
