{
  "@timestamp": "2026-04-17T16:01:37.787Z",
  "cloud": {
    "provider": "aws",
    "region": "ap-southeast-3",
    "account": { "id": "501938274650", "name": "globex-security-tooling" },
    "service": { "name": "connect" }
  },
  "aws": {
    "dimensions": { "InstanceId": "dfx1ws44-jpw2-fvez-ljzs-kclace1c9a", "MetricGroup": "Queue" },
    "connect": {
      "instance_id": "dfx1ws44-jpw2-fvez-ljzs-kclace1c9a",
      "contact_id": "8n2innpl-j77d-h2i5",
      "channel": "CHAT",
      "initiation_method": "INBOUND",
      "queue_name": "TechSupport",
      "agent_id": "agent-bob",
      "duration_seconds": 103,
      "hold_duration_seconds": 65,
      "queue_wait_time_seconds": 208,
      "disconnect_reason": "AGENT_DISCONNECT",
      "sentiment_overall": "MIXED",
      "contact_lens_enabled": true,
      "lex_bot_interacted": true,
      "initiation_timestamp": "2026-04-17T15:59:54.787Z",
      "disconnect_timestamp": "2026-04-17T16:01:37.787Z",
      "customer_endpoint": "+18550389091",
      "system_endpoint": "+18008033951",
      "metrics": {
        "ContactsQueued": { "sum": 1 },
        "ContactsHandled": { "sum": 1 },
        "ContactsAbandoned": { "sum": 0 },
        "ContactsHoldAbandonment": { "sum": 0 },
        "AverageHandleTime": { "avg": 103 },
        "AverageAfterContactWorkTime": { "avg": 167 },
        "AverageQueueAnswerTime": { "avg": 112 },
        "ServiceLevel": { "avg": 92.53870366733358 },
        "OccupancyTime": { "avg": 51.194121482349146 }
      }
    },
    "s3": {
      "bucket": {
        "name": "aws-connect-logs-501938274650",
        "arn": "arn:aws:s3:::aws-connect-logs-501938274650"
      },
      "object": {
        "key": "AWSLogs/501938274650/connect/ap-southeast-3/2026/04/17/connect_GCVPZINLKEM.log.gz"
      }
    },
    "cloudwatch": {
      "log_group": "/aws/connect/logs",
      "log_stream": "ap-southeast-3/zb1ch07h",
      "ingestion_time": "2026-04-17T16:01:38.442Z"
    }
  },
  "event": {
    "duration": 103000000000,
    "outcome": "success",
    "category": ["host", "session"],
    "dataset": "aws.connect",
    "provider": "connect.amazonaws.com",
    "module": "aws"
  },
  "message": "Connect INBOUND: TechSupport agent=agent-bob, 103s, MIXED",
  "log": { "level": "info" },
  "service": { "name": "connect", "type": "aws" },
  "ecs": { "version": "8.11.0" },
  "data_stream": { "type": "logs", "dataset": "aws.connect", "namespace": "default" },
  "agent": {
    "type": "filebeat",
    "version": "8.18.0",
    "name": "filebeat-aws-ap-southeast-3",
    "ephemeral_id": "9ds8ogeip7t"
  },
  "input": { "type": "aws-cloudwatch" }
}
