{
  "@timestamp": "2026-04-22T16:10:07.528Z",
  "cloud": {
    "provider": "aws",
    "region": "eu-south-1",
    "account": { "id": "293847561023", "name": "globex-staging" },
    "service": { "name": "drs" }
  },
  "aws": {
    "dimensions": { "SourceServerId": "s-d74v4atufbf" },
    "drs": {
      "source_server_id": "s-d74v4atufbf",
      "source_hostname": "web-server-01",
      "replication_status": "InProgress",
      "lag_duration_seconds": 22,
      "data_replication_state": "Continuous",
      "ebs_volume_count": 1,
      "staging_area": "us-west-2",
      "recovery_point_objective_seconds": 30
    },
    "s3": {
      "bucket": {
        "name": "aws-drs-logs-293847561023",
        "arn": "arn:aws:s3:::aws-drs-logs-293847561023"
      },
      "object": { "key": "AWSLogs/293847561023/drs/eu-south-1/2026/04/22/drs_NO2VNQZ0NL.log.gz" }
    },
    "cloudwatch": {
      "log_group": "/aws/drs/logs",
      "log_stream": "eu-south-1/8yhzilf6",
      "ingestion_time": "2026-04-22T16:10:08.435Z"
    }
  },
  "event": {
    "action": "SourceServerDisconnected",
    "outcome": "success",
    "category": ["host"],
    "dataset": "aws.drs",
    "provider": "drs.amazonaws.com",
    "module": "aws"
  },
  "message": "DRS web-server-01: replication InProgress, RPO 30s",
  "log": { "level": "info" },
  "service": { "name": "drs", "type": "aws" },
  "ecs": { "version": "8.11.0" },
  "data_stream": { "type": "logs", "dataset": "aws.drs", "namespace": "default" },
  "agent": {
    "type": "filebeat",
    "version": "8.18.0",
    "name": "filebeat-aws-eu-south-1",
    "ephemeral_id": "3vxnfeygvtn"
  },
  "input": { "type": "aws-cloudwatch" }
}
