{
  "@timestamp": "2026-04-13T10:53:45.336Z",
  "cloud": {
    "provider": "aws",
    "region": "us-east-2",
    "account": { "id": "501938274650", "name": "globex-security-tooling" },
    "service": { "name": "gamelift" }
  },
  "aws": {
    "dimensions": {
      "FleetId": "fleet-yzu9o5bw",
      "Location": "eu-west-1",
      "MetricGroups": "All",
      "OperatingSystem": "AMAZON_LINUX_2"
    },
    "gamelift": {
      "fleet_id": "fleet-yzu9o5bw",
      "fleet_name": "game-fleet-prod",
      "event_type": "MatchmakingTimedOut",
      "game_session_id": "arn:aws:gamelift:us-east-2::gamesession/game-fleet-prod/nm4strueek",
      "current_player_sessions": 7,
      "maximum_player_sessions": 50,
      "instance_type": "c5.large",
      "instance_count": 17,
      "desired_instances": 32,
      "idle_instances": 4,
      "matchmaking_configuration": "BalancedMatch",
      "matchmaking_ticket_id": "7d8i58tg6dq",
      "matchmaking_duration_seconds": 22,
      "metrics": {
        "ActiveInstances": { "avg": 87 },
        "IdleInstances": { "avg": 8 },
        "PercentIdleInstances": { "avg": 10.945579583371297 },
        "DesiredInstances": { "avg": 75 },
        "MinInstances": { "avg": 2 },
        "MaxInstances": { "avg": 100 },
        "InstanceInterruptions": { "sum": 0 },
        "ActiveGameSessions": { "avg": 407 },
        "ActivatingGameSessions": { "avg": 49 },
        "AvailableGameSessions": { "avg": 120 },
        "ActivePlayerSessions": { "avg": 2373 },
        "CurrentPlayerSessions": { "avg": 1012 },
        "PlayerSessionActivations": { "sum": 6 }
      }
    },
    "s3": {
      "bucket": {
        "name": "aws-gamelift-logs-501938274650",
        "arn": "arn:aws:s3:::aws-gamelift-logs-501938274650"
      },
      "object": {
        "key": "AWSLogs/501938274650/gamelift/us-east-2/2026/04/13/gamelift_AQAZGFWEP6Q.log.gz"
      }
    },
    "cloudwatch": {
      "log_group": "/aws/gamelift/logs",
      "log_stream": "us-east-2/fsnoxu2g",
      "ingestion_time": "2026-04-13T10:53:45.840Z"
    }
  },
  "event": {
    "outcome": "success",
    "category": ["process", "network"],
    "dataset": "aws.gamelift",
    "provider": "gamelift.amazonaws.com",
    "duration": 5275908000000,
    "module": "aws"
  },
  "message": "GameLift game-fleet-prod: MatchmakingTimedOut",
  "log": { "level": "warn" },
  "host": { "name": "ip-4-194-59-55.ec2.internal", "hostname": "gamelift-vgoa0zb5" },
  "service": { "name": "gamelift", "type": "aws" },
  "ecs": { "version": "8.11.0" },
  "data_stream": { "type": "logs", "dataset": "aws.gamelift", "namespace": "default" },
  "agent": {
    "type": "filebeat",
    "version": "8.18.0",
    "name": "filebeat-aws-us-east-2",
    "ephemeral_id": "nq68vwuqb5"
  },
  "input": { "type": "aws-cloudwatch" }
}
