{
  "@timestamp": "2026-04-21T16:58:54.847Z",
  "cloud": {
    "provider": "aws",
    "region": "ap-south-2",
    "account": { "id": "738291046572", "name": "globex-development" },
    "service": { "name": "imagebuilder" }
  },
  "aws": {
    "dimensions": { "PipelineName": "amazon-linux-cis", "Phase": "BUILD" },
    "imagebuilder": {
      "pipeline_name": "amazon-linux-cis",
      "image_version": "5.6.5/1",
      "phase": "BUILD",
      "phase_status": "COMPLETED",
      "duration_seconds": 1464,
      "os": "Ubuntu 22.04",
      "recipe_name": "docker-host",
      "ami_id": "ami-ax8pwww0",
      "metrics": {
        "BuildDuration": { "avg": 1464 },
        "ImageBuildSuccessCount": { "sum": 1 },
        "ImageBuildFailureCount": { "sum": 0 },
        "ComponentBuildDuration": { "avg": 1020 }
      }
    },
    "s3": {
      "bucket": {
        "name": "aws-imagebuilder-logs-738291046572",
        "arn": "arn:aws:s3:::aws-imagebuilder-logs-738291046572"
      },
      "object": {
        "key": "AWSLogs/738291046572/imagebuilder/ap-south-2/2026/04/21/imagebuilder_0YQAL7NR9OW.log.gz"
      }
    },
    "cloudwatch": {
      "log_group": "/aws/imagebuilder/logs",
      "log_stream": "ap-south-2/9rhi37ka",
      "ingestion_time": "2026-04-21T16:58:55.627Z"
    }
  },
  "event": {
    "category": ["process"],
    "duration": 1464000000000,
    "outcome": "success",
    "dataset": "aws.imagebuilder",
    "provider": "imagebuilder.amazonaws.com",
    "module": "aws"
  },
  "message": "EC2 Image Builder: amazon-linux-cis - BUILD phase STARTED",
  "log": { "level": "info" },
  "service": { "name": "imagebuilder", "type": "aws" },
  "ecs": { "version": "8.11.0" },
  "data_stream": { "type": "logs", "dataset": "aws.imagebuilder", "namespace": "default" },
  "agent": {
    "type": "filebeat",
    "version": "8.18.0",
    "name": "filebeat-aws-ap-south-2",
    "ephemeral_id": "srpto5iuzbn"
  },
  "input": { "type": "aws-cloudwatch" }
}
