{
  "@timestamp": "2026-04-21T16:58:54.847Z",
  "cloud": {
    "provider": "aws",
    "region": "ap-northeast-3",
    "account": { "id": "293847561023", "name": "globex-staging" },
    "service": { "name": "redshift" }
  },
  "aws": {
    "dimensions": { "ClusterIdentifier": "reporting-cluster", "NodeID": "Compute-3" },
    "cloudwatch": {
      "log_group": "/aws/redshift/cluster/reporting-cluster/userlog",
      "log_stream": "reporting-cluster/userlog/2026-04-21",
      "ingestion_time": "2026-04-21T16:58:55.756Z"
    },
    "redshift": {
      "cluster_id": "reporting-cluster",
      "node_type": "dc2.8xlarge",
      "number_of_nodes": 16,
      "database": "analytics",
      "schema": "raw",
      "user": "dbt_runner",
      "pid": 72186,
      "xid": 2988482,
      "query_id": 1151918,
      "log_type": "userlog",
      "duration_microseconds": 37356292,
      "rows_returned": 1104383,
      "rows_affected": 1104383,
      "bytes_scanned": 10584387478,
      "query_type": "VACUUM",
      "source_ip": "49.5.62.157",
      "source_port": 34276,
      "application_name": "psql",
      "wlm": {
        "queue_name": "superuser",
        "slot_count": 1,
        "queue_wait_ms": 798,
        "service_class": 7
      },
      "metrics": {
        "CPUUtilization": { "avg": 24.251970514884864 },
        "PercentageDiskSpaceUsed": { "avg": 68.47296282533293 },
        "DatabaseConnections": { "avg": 82 },
        "HealthStatus": { "avg": 1 },
        "MaintenanceMode": { "avg": 0 },
        "NetworkReceiveThroughput": { "avg": 910795328 },
        "NetworkTransmitThroughput": { "avg": 582298617 },
        "QueriesCompletedPerSecond": { "avg": 242.26414790736277 },
        "QueryDuration": { "avg": 15085.936419497377 },
        "QueryRuntimeBreakdown": { "avg": 22088.309624379177 },
        "ReadIOPS": { "avg": 3822 },
        "ReadLatency": { "avg": 0.008395085107553206 },
        "ReadThroughput": { "avg": 848510590 },
        "WLMQueriesCompletedPerSecond": { "avg": 123.71297813808796 },
        "WLMQueryDuration": { "avg": 8723.50215051074 },
        "WLMRunningSlotCount": { "avg": 41 },
        "WLMQueueLength": { "avg": 3 },
        "WLMQueueWaitTime": { "avg": 217.8682564480805 },
        "WriteIOPS": { "avg": 3628 },
        "WriteLatency": { "avg": 0.057365521993247376 },
        "WriteThroughput": { "avg": 16383122 }
      }
    },
    "s3": {
      "bucket": {
        "name": "aws-redshift-logs-293847561023",
        "arn": "arn:aws:s3:::aws-redshift-logs-293847561023"
      },
      "object": {
        "key": "AWSLogs/293847561023/redshift/ap-northeast-3/2026/04/21/redshift_B2M9EV35E1A.log.gz"
      }
    }
  },
  "db": {
    "user": { "name": "dbt_runner" },
    "name": "analytics",
    "statement": "VACUUM DELETE ONLY raw.fact_events TO 95 PERCENT",
    "type": "sql"
  },
  "source": { "ip": "49.5.62.157", "port": 34276 },
  "event": {
    "duration": 37356292111.63991,
    "outcome": "success",
    "category": ["database"],
    "dataset": "aws.redshift",
    "provider": "redshift.amazonaws.com",
    "module": "aws"
  },
  "message": "'2026-04-21 16:58:54.847 UTC [ db=analytics user=rdsdb pid=72186 userid=1 xid=2988482 ]' LOG: alter user dbt_runner set search_path to 'raw'",
  "log": { "level": "info" },
  "service": { "name": "redshift", "type": "aws" },
  "ecs": { "version": "8.11.0" },
  "data_stream": { "type": "logs", "dataset": "aws.redshift", "namespace": "default" },
  "agent": {
    "type": "filebeat",
    "version": "8.18.0",
    "name": "filebeat-aws-ap-northeast-3",
    "ephemeral_id": "zouse687pnr"
  },
  "input": { "type": "aws-cloudwatch" }
}
