{
  "@timestamp": "2026-04-10T11:57:57.329Z",
  "cloud": {
    "provider": "aws",
    "region": "us-east-2",
    "account": { "id": "814726593401", "name": "globex-production" },
    "service": { "name": "supplychain" }
  },
  "aws": {
    "dimensions": { "InstanceId": "arn:aws:scn:us-east-2:814726593401:instance/vrzjp3ek3o" },
    "supplychain": {
      "instance_id": "arn:aws:scn:us-east-2:814726593401:instance/vrzjp3ek3o",
      "instance_name": "apac-logistics",
      "namespace": "aws.supply_chain.collaboration",
      "event_type": "scn.data.inventory",
      "job_status": "SUCCESS",
      "record_count": 686508,
      "forecast_horizon_days": 40,
      "data_lake_dataset": "supplier_lead_times"
    },
    "s3": {
      "bucket": {
        "name": "aws-supplychain-logs-814726593401",
        "arn": "arn:aws:s3:::aws-supplychain-logs-814726593401"
      },
      "object": {
        "key": "AWSLogs/814726593401/supplychain/us-east-2/2026/04/10/supplychain_EHL4NHLLD6.log.gz"
      }
    },
    "cloudwatch": {
      "log_group": "/aws/supplychain/logs",
      "log_stream": "us-east-2/vuc6aerf",
      "ingestion_time": "2026-04-10T11:57:57.890Z"
    }
  },
  "event": {
    "action": "CreateInstance",
    "outcome": "success",
    "category": ["process"],
    "dataset": "aws.supplychain",
    "provider": "scn.amazonaws.com",
    "module": "aws"
  },
  "message": "Supply Chain CreateInstance: instance=apac-logistics event=scn.data.inventory status=SUCCESS",
  "log": { "level": "info" },
  "service": { "name": "supplychain", "type": "aws" },
  "ecs": { "version": "8.11.0" },
  "data_stream": { "type": "logs", "dataset": "aws.supplychain", "namespace": "default" },
  "agent": {
    "type": "filebeat",
    "version": "8.18.0",
    "name": "filebeat-aws-us-east-2",
    "ephemeral_id": "r1objpiff9"
  },
  "input": { "type": "aws-cloudwatch" }
}
