{
  "@timestamp": "2026-05-19T12:26:13.277Z",
  "cloud": {
    "provider": "aws",
    "region": "us-west-2",
    "account": { "id": "164820739518", "name": "globex-shared-services" },
    "service": { "name": "translate" }
  },
  "aws": {
    "dimensions": { "SourceLanguage": "it", "TargetLanguage": "zh" },
    "translate": {
      "source_language_code": "it",
      "target_language_code": "zh",
      "characters_translated": 241218,
      "applied_terminology": "product-terms",
      "duration_ms": 59,
      "metrics": {
        "SuccessfulRequestCount": { "sum": 1 },
        "ThrottledCount": { "sum": 0 },
        "UserErrorCount": { "sum": 0 },
        "ServerErrorCount": { "sum": 0 },
        "CharacterCount": { "sum": 3543 },
        "ResponseTime": { "avg": 118.76379718419116 }
      }
    },
    "s3": {
      "bucket": {
        "name": "aws-translate-logs-164820739518",
        "arn": "arn:aws:s3:::aws-translate-logs-164820739518"
      },
      "object": {
        "key": "AWSLogs/164820739518/translate/us-west-2/2026/05/19/translate_0UYERI52WA1OH0NGY3UC.log.gz"
      }
    },
    "cloudwatch": {
      "log_group": "/aws/translate/logs",
      "log_stream": "us-west-2/t1jovwdx",
      "ingestion_time": "2026-05-19T12:26:14.223Z"
    }
  },
  "event": {
    "duration": 58777346.60889555,
    "outcome": "success",
    "category": ["process"],
    "dataset": "aws.translate",
    "provider": "translate.amazonaws.com",
    "module": "aws"
  },
  "message": "Translate it->zh: 241,218 chars in 59ms",
  "log": { "level": "info" },
  "service": { "name": "translate", "type": "aws" },
  "ecs": { "version": "8.11.0" },
  "data_stream": { "type": "logs", "dataset": "aws.translate", "namespace": "default" },
  "agent": {
    "type": "filebeat",
    "version": "8.18.0",
    "name": "filebeat-aws-us-west-2",
    "ephemeral_id": "qfwurfmdb9cyyrldaylq45aihvwucco3y13d"
  },
  "input": { "type": "aws-cloudwatch" }
}
