{
  "@timestamp": "2026-04-08T15:12:15.029Z",
  "cloud": {
    "provider": "aws",
    "region": "ap-southeast-1",
    "account": { "id": "293847561023", "name": "globex-staging" },
    "service": { "name": "ipam" }
  },
  "aws": {
    "dimensions": { "PoolId": "ipam-pool-11wpm5n0", "ScopeId": "ipam-scope-ordqbl8j" },
    "vpcipam": {
      "pool_id": "ipam-pool-11wpm5n0",
      "scope_id": "ipam-scope-ordqbl8j",
      "allocation_id": "ipam-alloc-8oj2qpzt",
      "cidr": "10.1.0.0/16",
      "allocation_type": "vpc",
      "metrics": { "allocations_count": 67, "free_count": 412, "used_count": 67 }
    },
    "s3": {
      "bucket": {
        "name": "aws-vpcipam-logs-293847561023",
        "arn": "arn:aws:s3:::aws-vpcipam-logs-293847561023"
      },
      "object": {
        "key": "AWSLogs/293847561023/vpcipam/ap-southeast-1/2026/04/08/vpcipam_M4F1MQK4I.log.gz"
      }
    },
    "cloudwatch": {
      "log_group": "/aws/vpcipam/logs",
      "log_stream": "ap-southeast-1/4slhbpn7",
      "ingestion_time": "2026-04-08T15:12:15.376Z"
    }
  },
  "event": {
    "outcome": "success",
    "category": ["network"],
    "dataset": "aws.vpcipam",
    "provider": "ec2.amazonaws.com",
    "duration": 78000000,
    "module": "aws"
  },
  "data_stream": { "type": "logs", "dataset": "aws.vpcipam", "namespace": "default" },
  "message": "VPC IPAM pool ipam-pool-11wpm5n0: allocated 10.1.0.0/16 (vpc), free=412",
  "log": { "level": "info" },
  "service": { "name": "vpcipam", "type": "aws" },
  "ecs": { "version": "8.11.0" },
  "agent": {
    "type": "filebeat",
    "version": "8.18.0",
    "name": "filebeat-aws-ap-southeast-1",
    "ephemeral_id": "kmg1o0uuowi"
  },
  "input": { "type": "aws-cloudwatch" }
}
