{
  "@timestamp": "2026-04-07T12:00:00.000Z",
  "time": "2026-04-07T12:00:00.0000000Z",
  "resourceId": "/subscriptions/1a2b3c4d-5e6f-7890-abcd-ef1234567890/resourceGroups/rg-network-88plq1/providers/Microsoft.HybridCompute/machines/arc-sql-qjgik",
  "operationName": "Microsoft.HybridCompute/machines/assessPatches/action",
  "category": "PatchAssessment",
  "resultType": "Success",
  "resultSignature": "4",
  "callerIpAddress": "200.30.44.156",
  "correlationId": "089a26f8-359d-4126-a060-b5653c1de6ff",
  "level": "Informational",
  "properties": { "patchesPendingCritical": 4, "assessmentAgeHours": 13.359878686539467 },
  "cloud": {
    "provider": "azure",
    "region": "eastus",
    "account": { "id": "1a2b3c4d-5e6f-7890-abcd-ef1234567890", "name": "Fabrikam-Prod" },
    "service": { "name": "Microsoft.HybridCompute/machines" }
  },
  "azure": {
    "arc": {
      "machine_name": "arc-sql-qjgik",
      "resource_group": "rg-network-88plq1",
      "category": "PatchAssessment",
      "correlation_id": "089a26f8-359d-4126-a060-b5653c1de6ff",
      "properties": { "patchesPendingCritical": 4, "assessmentAgeHours": 13.359878686539467 }
    }
  },
  "event": {
    "outcome": "success",
    "duration": 357997789584,
    "module": "azure",
    "dataset": "azure.arc"
  },
  "message": "Arc arc-sql-qjgik: patch scan fresh",
  "service": { "name": "arc", "type": "azure" },
  "log": { "level": "info" },
  "ecs": { "version": "8.11.0" },
  "data_stream": { "type": "logs", "dataset": "azure.arc", "namespace": "default" },
  "agent": {
    "type": "elastic-agent",
    "version": "8.18.0",
    "name": "elastic-agent-azure-eastus",
    "id": "6f6w394lpe20gr3og5i7mbu6svlrfesu0l1k"
  },
  "input": { "type": "azure-eventhub" }
}
