{
  "@timestamp": "2026-04-07T12:00:00.000Z",
  "cloud": {
    "provider": "azure",
    "region": "southeastasia",
    "account": { "id": "8f6b5c4d-3e2a-1098-7654-3210fedcba98", "name": "Contoso-Platform" },
    "service": { "name": "Microsoft.Security/alerts" }
  },
  "azure": {
    "defender": {
      "alert_id": "dc19ndtcmc",
      "alert_name": "Unusual volume of data extracted from storage account",
      "severity": "High",
      "status": "Active",
      "resource_group": "rg-app-hkvhu2",
      "compromised_entity": "stzt1nzxgiry",
      "source_ip": "144.77.88.114",
      "intent": "Exfiltration"
    }
  },
  "source": { "ip": "144.77.88.114" },
  "event": {
    "kind": "alert",
    "outcome": "failure",
    "module": "azure",
    "dataset": "azure.defender"
  },
  "message": "Defender: possible data exfiltration from stzt1nzxgiry",
  "log": { "level": "error" },
  "service": { "name": "defender", "type": "azure" },
  "ecs": { "version": "8.11.0" },
  "data_stream": { "type": "logs", "dataset": "azure.defender", "namespace": "default" },
  "agent": {
    "type": "elastic-agent",
    "version": "8.18.0",
    "name": "elastic-agent-azure-southeastasia",
    "id": "48bxdzppxgi"
  },
  "input": { "type": "http_endpoint" },
  "category": "Administrative",
  "resourceId": "/subscriptions/8f6b5c4d-3e2a-1098-7654-3210fedcba98/resourcegroups/rg-app-hkvhu2/providers/Microsoft.Security/alerts/defender",
  "operationName": { "localizedValue": "Write", "value": "defender/action" },
  "properties": {
    "defender": {
      "alert_id": "dc19ndtcmc",
      "alert_name": "Unusual volume of data extracted from storage account",
      "severity": "High",
      "status": "Active",
      "resource_group": "rg-app-hkvhu2",
      "compromised_entity": "stzt1nzxgiry",
      "source_ip": "144.77.88.114",
      "intent": "Exfiltration"
    }
  }
}
