{
  "@timestamp": "2026-04-07T12:00:00.000Z",
  "time": "2026-04-07T12:00:00.000Z",
  "resourceId": "/subscriptions/1a2b3c4d-5e6f-7890-abcd-ef1234567890/resourceGroups/rg-analytics-jykjcm/providers/Microsoft.Cdn/profiles/front-cvr0k",
  "operationName": "Microsoft.Cdn/profiles/write",
  "category": "Administrative",
  "resultType": "Success",
  "resultSignature": "201",
  "callerIpAddress": "79.67.156.114",
  "correlationId": "lc88xu18em",
  "level": "Information",
  "identity": {
    "claims": {
      "appid": "vbhbdgo1-09l6-xd4n-30sm-pcb90g7lp8",
      "appidacr": "2",
      "iss": "https://sts.windows.net/crbgzus9-u3bt-fujv-fy81-4yb0gmut8f/",
      "aud": "https://management.azure.com/",
      "http://schemas.microsoft.com/identity/claims/objectidentifier": "3s6rq5vd-6xad-f6l4-ac8s-wa5r498zt4"
    }
  },
  "properties": {
    "statusCode": 201,
    "statusMessage": {
      "status": "Succeeded",
      "correlationRequestId": "co83oatx-vsxf-uh4z-7xhp-1vf7c6xs6w8"
    },
    "serviceRequestId": "co83oatx-vsxf-uh4z-7xhp-1vf7c6xs6w8",
    "eventCategory": "Administrative"
  },
  "cloud": {
    "provider": "azure",
    "region": "westus3",
    "account": { "id": "1a2b3c4d-5e6f-7890-abcd-ef1234567890", "name": "Fabrikam-Prod" },
    "service": { "name": "Microsoft.Cdn/profiles" }
  },
  "azure": {
    "front_door": {
      "resource_group": "rg-analytics-jykjcm",
      "resource_name": "front-cvr0k",
      "resource_id": "/subscriptions/1a2b3c4d-5e6f-7890-abcd-ef1234567890/resourceGroups/rg-analytics-jykjcm/providers/Microsoft.Cdn/profiles/front-cvr0k",
      "operation_name": "Microsoft.Cdn/profiles/write",
      "status": "Success",
      "correlation_id": "lc88xu18em",
      "http_status": 201,
      "duration_ms": 5774,
      "category": "Administrative",
      "level": "Information",
      "caller_ip_address": "79.67.156.114",
      "result_signature": "201",
      "properties": {
        "statusCode": 201,
        "statusMessage": {
          "status": "Succeeded",
          "correlationRequestId": "co83oatx-vsxf-uh4z-7xhp-1vf7c6xs6w8"
        },
        "serviceRequestId": "co83oatx-vsxf-uh4z-7xhp-1vf7c6xs6w8",
        "eventCategory": "Administrative"
      }
    }
  },
  "event": {
    "outcome": "success",
    "duration": 69966,
    "action": "Microsoft.Cdn/profiles/write",
    "module": "azure",
    "dataset": "azure.front_door"
  },
  "message": "ARM audit: principal completed Microsoft.Cdn/profiles/write on front-cvr0k in rg-analytics-jykjcm (westus3) latencyMs=5774",
  "service": { "name": "front-door", "type": "azure" },
  "log": { "level": "info" },
  "ecs": { "version": "8.11.0" },
  "data_stream": { "type": "logs", "dataset": "azure.front_door", "namespace": "default" },
  "agent": {
    "type": "elastic-agent",
    "version": "8.18.0",
    "name": "elastic-agent-azure-westus3",
    "id": "0cjsfwiyza4g"
  },
  "input": { "type": "azure-eventhub" }
}
