{
  "@timestamp": "2026-04-07T12:00:00.000Z",
  "time": "2026-04-07T12:00:00.0000000Z",
  "resourceId": "/subscriptions/a3f8c2e1-7b4d-4f9a-8e2c-1d5f6a7b8c9d/resourceGroups/rg-shared-it8a26/providers/Microsoft.DBforPostgreSQL/flexibleServers/psql-lz1he",
  "operationName": "pg_stat_statements_sample",
  "category": "PostgreSQLLogs",
  "resultType": "Success",
  "resultSignature": "CPU",
  "callerIpAddress": "224.49.77.36",
  "correlationId": "5f1067a4-e5c3-42d4-b180-75e29b315932",
  "level": "Information",
  "properties": {
    "database": "app",
    "queryId": "pw0xqsteak46",
    "meanTimeMs": 25.794065292651332,
    "calls": 20698,
    "sharedBlksHit": 3480113,
    "waitEvent": "CPU"
  },
  "cloud": {
    "provider": "azure",
    "region": "uaenorth",
    "account": { "id": "a3f8c2e1-7b4d-4f9a-8e2c-1d5f6a7b8c9d", "name": "Meridian-Platform" },
    "service": { "name": "Microsoft.DBforPostgreSQL/servers" }
  },
  "azure": {
    "database_for_postgresql": {
      "server": "psql-lz1he",
      "resource_group": "rg-shared-it8a26",
      "category": "PostgreSQLLogs",
      "correlation_id": "5f1067a4-e5c3-42d4-b180-75e29b315932",
      "properties": {
        "database": "app",
        "queryId": "pw0xqsteak46",
        "meanTimeMs": 25.794065292651332,
        "calls": 20698,
        "sharedBlksHit": 3480113,
        "waitEvent": "CPU"
      }
    }
  },
  "event": {
    "kind": "event",
    "category": ["database"],
    "type": ["access"],
    "action": "pg_stat_statements_sample",
    "outcome": "success",
    "duration": 39051193,
    "module": "azure",
    "dataset": "azure.postgresql"
  },
  "message": "PostgreSQL psql-lz1he: query stats OK mean 25.8ms",
  "service": { "name": "database-for-postgresql", "type": "azure" },
  "log": { "level": "info" },
  "ecs": { "version": "8.11.0" },
  "data_stream": { "type": "logs", "dataset": "azure.postgresql", "namespace": "default" },
  "agent": {
    "type": "elastic-agent",
    "version": "8.18.0",
    "name": "elastic-agent-azure-uaenorth",
    "id": "y2ntsdwyymo8hqiskt7o5019s27ebq2mm6ee"
  },
  "input": { "type": "azure-eventhub" }
}
