{
  "@timestamp": "2026-04-07T12:00:00.000Z",
  "cloud": {
    "provider": "azure",
    "region": "brazilsouth",
    "account": { "id": "1a2b3c4d-5e6f-7890-abcd-ef1234567890", "name": "Fabrikam-Prod" },
    "service": { "name": "Microsoft.Azure/express.route" }
  },
  "azure": {
    "express_route": {
      "resource_group": "rg-prod-m7p5j5",
      "resource_name": "expressroute-o7vb5",
      "resource_id": "/subscriptions/1a2b3c4d-5e6f-7890-abcd-ef1234567890/resourceGroups/rg-prod-m7p5j5/providers/Microsoft.Azure/express.route/expressroute-o7vb5",
      "operation_name": "Microsoft.Azure/express.route/Get",
      "status": "Succeeded",
      "correlation_id": "z7lwft4u92l",
      "http_status": 201,
      "duration_ms": 5115
    }
  },
  "event": {
    "outcome": "success",
    "duration": 6568886,
    "action": "Get",
    "module": "azure",
    "dataset": "azure.express_route"
  },
  "message": "Azure expressroute-circuit: Get completed for expressroute-o7vb5 in rg-prod-m7p5j5",
  "service": { "name": "express-route", "type": "azure" },
  "log": { "level": "info" },
  "ecs": { "version": "8.11.0" },
  "data_stream": { "type": "logs", "dataset": "azure.express_route", "namespace": "default" },
  "agent": {
    "type": "elastic-agent",
    "version": "8.18.0",
    "name": "elastic-agent-azure-brazilsouth",
    "id": "hqymljufgaa"
  },
  "input": { "type": "azure-eventhub" },
  "category": "Administrative",
  "resourceId": "/subscriptions/1a2b3c4d-5e6f-7890-abcd-ef1234567890/resourcegroups/rg-prod-m7p5j5/providers/Microsoft.Azure/express.route/express-route",
  "operationName": { "localizedValue": "Get", "value": "express-route/action" },
  "properties": {
    "express_route": {
      "resource_group": "rg-prod-m7p5j5",
      "resource_name": "expressroute-o7vb5",
      "resource_id": "/subscriptions/1a2b3c4d-5e6f-7890-abcd-ef1234567890/resourceGroups/rg-prod-m7p5j5/providers/Microsoft.Azure/express.route/expressroute-o7vb5",
      "operation_name": "Microsoft.Azure/express.route/Get",
      "status": "Succeeded",
      "correlation_id": "z7lwft4u92l",
      "http_status": 201,
      "duration_ms": 5115
    }
  }
}
