{
  "@timestamp": "2026-04-07T12:00:00.000Z",
  "cloud": {
    "provider": "azure",
    "region": "northcentralus",
    "account": { "id": "aaaaaaaa-bbbb-cccc-dddd-eeeeeeeeeeee", "name": "Northwind-Dev" },
    "service": { "name": "Microsoft.Logic/workflows" }
  },
  "azure": {
    "logic_apps": {
      "workflow_name": "data-sync",
      "workflow_id": "ejzjuxe3k8",
      "resource_group": "rg-app-xzcorr",
      "run_id": "s6ihm80nvnb",
      "action_name": "ParseJSON",
      "action_type": "Http",
      "trigger_name": "recurrence",
      "status": "Succeeded",
      "duration_ms": 4846
    }
  },
  "event": {
    "outcome": "success",
    "duration": 4846000000,
    "module": "azure",
    "dataset": "azure.logic_apps"
  },
  "message": "Logic Apps data-sync: run s6ihm80nvnb succeeded (4846ms)",
  "service": { "name": "logic-apps", "type": "azure" },
  "log": { "level": "info" },
  "ecs": { "version": "8.11.0" },
  "data_stream": { "type": "logs", "dataset": "azure.logic_apps", "namespace": "default" },
  "agent": {
    "type": "elastic-agent",
    "version": "8.18.0",
    "name": "elastic-agent-azure-northcentralus",
    "id": "2wlfnx8u1bp"
  },
  "input": { "type": "azure-eventhub" },
  "category": "Administrative",
  "resourceId": "/subscriptions/aaaaaaaa-bbbb-cccc-dddd-eeeeeeeeeeee/resourcegroups/rg-app-xzcorr/providers/Microsoft.Logic/workflows/logic-apps",
  "operationName": { "localizedValue": "Write", "value": "logic-apps/action" },
  "properties": {
    "logic_apps": {
      "workflow_name": "data-sync",
      "workflow_id": "ejzjuxe3k8",
      "resource_group": "rg-app-xzcorr",
      "run_id": "s6ihm80nvnb",
      "action_name": "ParseJSON",
      "action_type": "Http",
      "trigger_name": "recurrence",
      "status": "Succeeded",
      "duration_ms": 4846
    }
  }
}
