{
  "@timestamp": "2026-04-07T12:00:00.000Z",
  "time": "2026-04-07T12:00:00.0000000Z",
  "resourceId": "/subscriptions/8f6b5c4d-3e2a-1098-7654-3210fedcba98/resourceGroups/rg-shared-ok46vs/providers/Microsoft.OperationalInsights/workspaces/law-0d138",
  "operationName": "Microsoft.SecurityInsights/alertRules/query",
  "category": "AnalyticsRuleExecution",
  "resultType": "Success",
  "resultSignature": "Completed",
  "callerIpAddress": "133.29.57.165",
  "correlationId": "2f056d4c-9043-424b-946e-538860850aed",
  "level": "Information",
  "properties": {
    "ruleId": "f3de697b-7d0e-42cb-80a1-280db1690f92",
    "ruleName": "Malware hash match",
    "runFrequency": "5M",
    "matchedEvents": 2428,
    "queryDurationMs": 31657,
    "status": "Completed",
    "correlationId": "2f056d4c-9043-424b-946e-538860850aed"
  },
  "cloud": {
    "provider": "azure",
    "region": "northeurope",
    "account": { "id": "8f6b5c4d-3e2a-1098-7654-3210fedcba98", "name": "Contoso-Platform" },
    "service": { "name": "Microsoft.SecurityInsights/alertRules" }
  },
  "azure": {
    "sentinel": {
      "workspace": "law-0d138",
      "resource_group": "rg-shared-ok46vs",
      "resource_id": "/subscriptions/8f6b5c4d-3e2a-1098-7654-3210fedcba98/resourceGroups/rg-shared-ok46vs/providers/Microsoft.OperationalInsights/workspaces/law-0d138",
      "category": "AnalyticsRule",
      "correlation_id": "2f056d4c-9043-424b-946e-538860850aed",
      "properties": {
        "ruleId": "f3de697b-7d0e-42cb-80a1-280db1690f92",
        "ruleName": "Malware hash match",
        "runFrequency": "5M",
        "matchedEvents": 2428,
        "queryDurationMs": 31657,
        "status": "Completed",
        "correlationId": "2f056d4c-9043-424b-946e-538860850aed"
      }
    }
  },
  "event": {
    "outcome": "success",
    "duration": 7713296129,
    "module": "azure",
    "dataset": "azure.sentinel"
  },
  "message": "Sentinel rule Malware hash match: matched 2428 events",
  "service": { "name": "sentinel", "type": "azure" },
  "log": { "level": "info" },
  "ecs": { "version": "8.11.0" },
  "data_stream": { "type": "logs", "dataset": "azure.sentinel", "namespace": "default" },
  "agent": {
    "type": "elastic-agent",
    "version": "8.18.0",
    "name": "elastic-agent-azure-northeurope",
    "id": "d54x9wdve4z92lyh8nusj681nn20da0nen06"
  },
  "input": { "type": "azure-eventhub" }
}
