{
  "@timestamp": "2026-04-07T12:00:00.000Z",
  "time": "2026-04-07T12:00:00.000Z",
  "resourceId": "/subscriptions/aaaaaaaa-bbbb-cccc-dddd-eeeeeeeeeeee/resourceGroups/rg-analytics-880fwl/providers/Microsoft.Web/staticSites/static-36hf2",
  "operationName": "Microsoft.Web/staticSites/delete",
  "category": "ServiceHealth",
  "resultType": "Accept",
  "resultSignature": "200",
  "callerIpAddress": "53.72.41.135",
  "correlationId": "0yqy45vibqy",
  "level": "Information",
  "identity": {
    "claims": {
      "http://schemas.xmlsoap.org/ws/2005/05/identity/claims/upn": "svc-cicd@northwind.com",
      "http://schemas.microsoft.com/identity/claims/objectidentifier": "k5n72wvy-4nc9-2wt6-ahxd-2np7jq3y8x7",
      "http://schemas.microsoft.com/identity/claims/tenantid": "005l3g4i-f72i-c43l-6war-uuemuyk1qcr"
    }
  },
  "properties": {
    "statusCode": 200,
    "statusMessage": {
      "status": "Succeeded",
      "correlationRequestId": "o20mwowp-1gdb-00qt-d1x0-nicq4vv819l"
    },
    "serviceRequestId": "o20mwowp-1gdb-00qt-d1x0-nicq4vv819l",
    "eventCategory": "Administrative"
  },
  "cloud": {
    "provider": "azure",
    "region": "uaenorth",
    "account": { "id": "aaaaaaaa-bbbb-cccc-dddd-eeeeeeeeeeee", "name": "Northwind-Dev" },
    "service": { "name": "Microsoft.Web/staticSites" }
  },
  "azure": {
    "static_web_apps": {
      "resource_group": "rg-analytics-880fwl",
      "resource_name": "static-36hf2",
      "resource_id": "/subscriptions/aaaaaaaa-bbbb-cccc-dddd-eeeeeeeeeeee/resourceGroups/rg-analytics-880fwl/providers/Microsoft.Web/staticSites/static-36hf2",
      "operation_name": "Microsoft.Web/staticSites/delete",
      "status": "Accept",
      "correlation_id": "0yqy45vibqy",
      "http_status": 200,
      "duration_ms": 2611,
      "category": "ServiceHealth",
      "level": "Information",
      "caller_ip_address": "53.72.41.135",
      "result_signature": "200",
      "properties": {
        "statusCode": 200,
        "statusMessage": {
          "status": "Succeeded",
          "correlationRequestId": "o20mwowp-1gdb-00qt-d1x0-nicq4vv819l"
        },
        "serviceRequestId": "o20mwowp-1gdb-00qt-d1x0-nicq4vv819l",
        "eventCategory": "Administrative"
      }
    }
  },
  "event": {
    "outcome": "success",
    "duration": 3172447,
    "action": "Microsoft.Web/staticSites/delete",
    "module": "azure",
    "dataset": "azure.static_web_apps"
  },
  "message": "AzureDiagnostics category=Operational service=static-web-apps op=Microsoft.Web/staticSites/delete target=static-36hf2 rg=rg-analytics-880fwl ms=2611 req=o20mwowp-1gdb-00qt-d1x0-nicq4vv819l",
  "service": { "name": "static-web-apps", "type": "azure" },
  "log": { "level": "info" },
  "ecs": { "version": "8.11.0" },
  "data_stream": { "type": "logs", "dataset": "azure.static_web_apps", "namespace": "default" },
  "agent": {
    "type": "elastic-agent",
    "version": "8.18.0",
    "name": "elastic-agent-azure-uaenorth",
    "id": "ei5z8tcztnp"
  },
  "input": { "type": "azure-eventhub" }
}
